elementfm_mcp_server/__init__.py
elementfm_mcp_server/server.py
elementfm_mcp_server-0.4.0.dist-info/METADATA
elementfm_mcp_server-0.4.0.dist-info/WHEEL
elementfm_mcp_server-0.4.0.dist-info/entry_points.txt
elementfm_mcp_server-0.4.0.dist-info/licenses/LICENSE
elementfm_mcp_server-0.4.0.dist-info/RECORD
