Metadata-Version: 2.4
Name: elementfm-mcp-server
Version: 0.4.0
Summary: MCP (Model Control Protocol) server for Element.fm, providing tools for managing podcasts
Project-URL: Homepage, https://element.fm
Project-URL: Repository, https://gitlab.com/elementfm/mcp
Project-URL: Documentation, https://gitlab.com/elementfm/docs
Author: Element.fm Team
License-Expression: GPL-3.0-or-later
License-File: LICENSE
Keywords: element.fm,mcp,podcast
Classifier: Development Status :: 4 - Beta
Classifier: Intended Audience :: Developers
Classifier: License :: OSI Approved :: GNU General Public License v3 or later (GPLv3+)
Classifier: Programming Language :: Python :: 3
Classifier: Programming Language :: Python :: 3.13
Classifier: Topic :: Multimedia :: Sound/Audio
Requires-Python: >=3.13
Requires-Dist: mcp[cli]>=1.6.0
Requires-Dist: pydantic>=2.11.1
Requires-Dist: requests>=2.32.3
